odoo/addons/sale_timesheet_order_line_no_update/README.rst
odoo/addons/sale_timesheet_order_line_no_update/__init__.py
odoo/addons/sale_timesheet_order_line_no_update/__manifest__.py
odoo/addons/sale_timesheet_order_line_no_update/i18n/it.po
odoo/addons/sale_timesheet_order_line_no_update/i18n/sale_timesheet_order_line_no_update.pot
odoo/addons/sale_timesheet_order_line_no_update/models/__init__.py
odoo/addons/sale_timesheet_order_line_no_update/models/account_analytic_line.py
odoo/addons/sale_timesheet_order_line_no_update/models/project.py
odoo/addons/sale_timesheet_order_line_no_update/models/res_config_settings.py
odoo/addons/sale_timesheet_order_line_no_update/readme/CONFIGURATION.rst
odoo/addons/sale_timesheet_order_line_no_update/readme/CONTEXT.rst
odoo/addons/sale_timesheet_order_line_no_update/readme/CONTRIBUTORS.rst
odoo/addons/sale_timesheet_order_line_no_update/readme/DESCRIPTION.rst
odoo/addons/sale_timesheet_order_line_no_update/static/description/icon.png
odoo/addons/sale_timesheet_order_line_no_update/static/description/index.html
odoo/addons/sale_timesheet_order_line_no_update/tests/__init__.py
odoo/addons/sale_timesheet_order_line_no_update/tests/test_sale_timesheet_order_line_no_update.py
odoo/addons/sale_timesheet_order_line_no_update/views/project.xml
odoo/addons/sale_timesheet_order_line_no_update/views/res_config_settings_views.xml
odoo14_addon_sale_timesheet_order_line_no_update-14.0.1.1.4.dist-info/METADATA
odoo14_addon_sale_timesheet_order_line_no_update-14.0.1.1.4.dist-info/WHEEL
odoo14_addon_sale_timesheet_order_line_no_update-14.0.1.1.4.dist-info/top_level.txt
odoo14_addon_sale_timesheet_order_line_no_update-14.0.1.1.4.dist-info/RECORD
